translateabc/__init__.py
translateabc/translateabc.py
translateabc/READMEhh/ai35/01/1.ipynb
translateabc/READMEhh/ai35/01/2.ipynb
translateabc/READMEhh/ai35/01/3.ipynb
translateabc/READMEhh/ai35/01/4.ipynb
translateabc/READMEhh/ai35/01/5.ipynb
translateabc/READMEhh/ai35/01/6.ipynb
translateabc/READMEhh/ai35/02/01.ipynb
translateabc/READMEhh/moni/bankmarketing.csv
translateabc/READMEhh/moni/bigdata01-8(1).ipynb
translateabc/READMEhh/pandas-exercise/1.csv
translateabc/READMEhh/pandas-exercise/1.ipynb
translateabc/READMEhh/pandas-exercise/2.csv
translateabc/READMEhh/pandas-exercise/output.csv
translateabc-1.0.2.dist-info/LICENSE
translateabc-1.0.2.dist-info/METADATA
translateabc-1.0.2.dist-info/WHEEL
translateabc-1.0.2.dist-info/top_level.txt
translateabc-1.0.2.dist-info/RECORD
