Metadata-Version: 2.1
Name: translateabc
Version: 1.0.2
Summary: translateabc
Home-page: https://github.com/pypa/sampleproject
Author: Linvery
Author-email: 1253445120@qq.com
Project-URL: Bug Tracker, https://github.com/pypa/sampleproject/issues
Classifier: Programming Language :: Python :: 3
Classifier: License :: OSI Approved :: MIT License
Classifier: Operating System :: OS Independent
Requires-Python: >=3.6
License-File: LICENSE
